cineapp_sdk/__init__.py
cineapp_sdk/cineapp_client.py
cineapp_sdk/cineapp_config.py
cineapp_sdk/schemas/__init__.py
cineapp_sdk/schemas/schemas.py
cineapp_sdk-0.1.1.dist-info/METADATA
cineapp_sdk-0.1.1.dist-info/WHEEL
cineapp_sdk-0.1.1.dist-info/top_level.txt
cineapp_sdk-0.1.1.dist-info/RECORD
